matchdb/__init__.py
matchdb/_modidx.py
matchdb/matchdb.py
matchdb-0.1.0.dist-info/LICENSE
matchdb-0.1.0.dist-info/METADATA
matchdb-0.1.0.dist-info/WHEEL
matchdb-0.1.0.dist-info/entry_points.txt
matchdb-0.1.0.dist-info/top_level.txt
matchdb-0.1.0.dist-info/RECORD
