Metadata-Version: 2.1
Name: matchdb
Version: 0.1.0
Summary: Suggesting people to connect with based on shared interests
Home-page: https://github.com/batmanscode/MatchDB
Author: batmanscode
Author-email: 
License: Apache Software License 2.0
Keywords: nbdev jupyter notebook python
Platform: UNKNOWN
Classifier: Development Status :: 4 - Beta
Classifier: Intended Audience :: Developers
Classifier: Natural Language :: English
Classifier: Programming Language :: Python :: 3.7
Classifier: Programming Language :: Python :: 3.8
Classifier: Programming Language :: Python :: 3.9
Classifier: Programming Language :: Python :: 3.10
Classifier: License :: OSI Approved :: Apache Software License
Requires-Python: >=3.7
Requires-Dist: deta (==1.1.0)
Requires-Dist: pandas (==1.2.5)
Requires-Dist: ulid-py (==1.1.0)
Provides-Extra: dev
